uniparser_classical_armenian/__init__.py
uniparser_classical_armenian/data/__init__.py
uniparser_classical_armenian/data/lexemes.txt
uniparser_classical_armenian/data/paradigms.txt
uniparser_classical_armenian-1.0.0.dist-info/LICENSE
uniparser_classical_armenian-1.0.0.dist-info/METADATA
uniparser_classical_armenian-1.0.0.dist-info/WHEEL
uniparser_classical_armenian-1.0.0.dist-info/top_level.txt
uniparser_classical_armenian-1.0.0.dist-info/RECORD
